fastgenerator/__init__.py
fastgenerator/add.py
fastgenerator/alembic.py
fastgenerator/app.py
fastgenerator/cli.py
fastgenerator/code.py
fastgenerator/config.py
fastgenerator/const.py
fastgenerator/create.py
fastgenerator/files.py
fastgenerator/format.py
fastgenerator/module.py
fastgenerator/utils.py
fastgenerator/uv.py
tests/__init__.py
tests/test_init.py
fastgenerator-0.1.dist-info/LICENSE
fastgenerator-0.1.dist-info/METADATA
fastgenerator-0.1.dist-info/WHEEL
fastgenerator-0.1.dist-info/entry_points.txt
fastgenerator-0.1.dist-info/top_level.txt
fastgenerator-0.1.dist-info/RECORD
