Metadata-Version: 2.1
Name: fastgenerator
Version: 0.1
Summary: A fast code generator CLI tool
Home-page: https://github.com/AlexDemure/fastgenerator
Author: Alexander Grishchenko
Author-email: alexanderdemure@gmail.com
Classifier: Programming Language :: Python :: 3
Classifier: License :: OSI Approved :: MIT License
Classifier: Operating System :: OS Independent
Requires-Python: >=3.8
License-File: LICENSE
Requires-Dist: pyyaml
Requires-Dist: typer
